ifs_ecs_logger/__init__.py
ifs_ecs_logger/constants.py
ifs_ecs_logger/formatter.py
ifs_ecs_logger-0.1.3.dist-info/licenses/LICENSE
ifs_ecs_logger-0.1.3.dist-info/METADATA
ifs_ecs_logger-0.1.3.dist-info/WHEEL
ifs_ecs_logger-0.1.3.dist-info/top_level.txt
ifs_ecs_logger-0.1.3.dist-info/RECORD
