Metadata-Version: 2.4
Name: ifs-ecs-logger
Version: 0.1.3
Summary: IFS-compliant ECS structured logger for CI/CD pipelines
Author: IFS Golden CI Team
License: MIT
Keywords: logging,ecs,elastic,ifs,structured,tekton
Classifier: Programming Language :: Python :: 3
Classifier: Programming Language :: Python :: 3.8
Classifier: Programming Language :: Python :: 3.9
Classifier: Programming Language :: Python :: 3.10
Classifier: Programming Language :: Python :: 3.11
Classifier: Programming Language :: Python :: 3.12
Classifier: Operating System :: OS Independent
Classifier: Topic :: System :: Logging
Classifier: Intended Audience :: Developers
Requires-Python: >=3.8
License-File: LICENSE
Requires-Dist: ecs-logging>=2.1.0
Requires-Dist: python-json-logger>=2.0.7
Dynamic: license-file
